tap_file/__init__.py
tap_file/data_stream.py
tap_file/dipole.py
tap_file/header_type.py
tap_file/magic.py
tap_file/profile.py
tap_file/tap_file_reader.py
tap_file/tap_file_writer.py
tap_file/tap_header.py
tap_file/tap_object.py
tap_file/tap_program.py
tap_file/tap_seq_data.py
tapfile-1.0.dist-info/LICENSE
tapfile-1.0.dist-info/METADATA
tapfile-1.0.dist-info/WHEEL
tapfile-1.0.dist-info/top_level.txt
tapfile-1.0.dist-info/RECORD
